Metadata-Version: 2.1
Name: equality-check
Version: 0.0.4
License: pscl
License-File: LICENSE
